setup.cfg
setup.py
gaetestbed/__init__.py
gaetestbed/base.py
gaetestbed/datastore.py
gaetestbed/functional.py
gaetestbed/mail.py
gaetestbed/memcache.py
gaetestbed/taskqueue.py
gaetestbed/unit.py
gaetestbed/web.py
gaetestbed.egg-info/PKG-INFO
gaetestbed.egg-info/SOURCES.txt
gaetestbed.egg-info/dependency_links.txt
gaetestbed.egg-info/top_level.txt
gaetestbed.egg-info/zip-safe