Metadata-Version: 1.0
Name: gaetestbed
Version: 0.12
Summary: GAE Testbed is a set of test cases to simplify testing on AppEngine
Home-page: http://jgeewax.github.com/gaetestbed
Author: JJ Geewax
Author-email: jj@geewax.org
License: GPL v2
Keywords: test testing app-engine google-app-engine gae unittest
Platform: UNKNOWN
Classifier: Development Status :: 4 - Beta
Classifier: Intended Audience :: Developers
Classifier: License :: OSI Approved :: GNU General Public License (GPL)
Classifier: Natural Language :: English
Classifier: Operating System :: OS Independent
Classifier: Programming Language :: Python
Classifier: Topic :: Software Development :: Libraries :: Python Modules
Classifier: Topic :: Software Development :: Testing
